{"cameraMode":{"drawMode":0,"name":"Shaded","section":"Shading Mode"},"sceneLighting":false,"audioPlay":false,"sceneViewState":{"m_AlwaysRefresh":false,"showFog":true,"showSkybox":false,"showFlares":true,"showImageEffects":true,"showParticleSystems":true,"showVisualEffectGraphs":true,"m_FxEnabled":true},"in2DMode":false,"pivot":{"x":-11.033011436462403,"y":4.758490562438965,"z":15.011383056640625},"rotation":{"x":0.3501244783401489,"y":0.37562358379364016,"z":-0.15586473047733308,"w":0.8438262343406677},"size":8.249600410461426,"orthographic":false}